proxmox_info/_version.py
proxmox_info/config.py
proxmox_info/pminfo.py
proxmox_info-1.0.9.dist-info/LICENSE
proxmox_info-1.0.9.dist-info/METADATA
proxmox_info-1.0.9.dist-info/WHEEL
proxmox_info-1.0.9.dist-info/entry_points.txt
proxmox_info-1.0.9.dist-info/top_level.txt
proxmox_info-1.0.9.dist-info/RECORD
