Metadata-Version: 2.1
Name: proxmox-info
Version: 1.0.9
Summary: A CLI utility to return various info from the Proxmox API.
Author-email: Jason Lingohr <jason@lucid.net.au>
Project-URL: Homepage, https://github.com/lingfish/proxmox-info
Project-URL: Issues, https://github.com/lingfish/proxmox-info/issues
Classifier: Programming Language :: Python :: 3
Classifier: License :: OSI Approved :: GNU General Public License v3 or later (GPLv3+)
Classifier: Operating System :: OS Independent
Requires-Python: >=3.9
License-File: LICENSE
Requires-Dist: proxmoxer
Requires-Dist: humanize
Requires-Dist: dynaconf
Requires-Dist: click
Requires-Dist: requests
Requires-Dist: pandas
Requires-Dist: rich
